markright/__init__.py
markright/cli.py
markright-1.1.1.dist-info/METADATA
markright-1.1.1.dist-info/WHEEL
markright-1.1.1.dist-info/entry_points.txt
markright-1.1.1.dist-info/top_level.txt
markright-1.1.1.dist-info/RECORD
