Metadata-Version: 2.1
Name: markright
Version: 1.1.1
Summary: Templateless markdown template engine
Home-page: https://gitlab.com/Vadimhtml/markright
Author: Vadimhtml
Author-email: i@vadimhtml.ru
License: MIT
Keywords: markdown template
Platform: UNKNOWN
Classifier: Development Status :: 4 - Beta
Classifier: License :: OSI Approved :: MIT License
Classifier: Programming Language :: Python :: 3
Classifier: Topic :: Software Development :: Libraries :: Python Modules
Classifier: Topic :: Utilities
